4-bit-ALU-Verilog/src/full_adder.v
 module full_adder(
  input  a, b, cin,
  output sum, cout);
  assign sum  = a ^ b ^ cin;
  assign cout = (a & b)|(b & cin)|(a & cin);
endmodule

4-bit-ALU-Verilog/src/adder_4bit.v
module adder_4bit(input [3:0]A,B,input cin
,output [3:0] sum,output cout);
wire a1,a2,a3;
full_adder add1(A[0],B[0],cin,sum[0],a1);// inistiating 4 full adder to get a 4bit adder
full_adder add2(A[1],B[1],a1,sum[1],a2);
full_adder add3(A[2],B[2],a2,sum[2],a3);
full_adder add4(A[3],B[3],a3,sum[3],cout);
endmodule

4-bit-ALU-Verilog/testbench/adder_4bit_tb.v
`timescale 1ns/1ps 

module adder_4bit_tb;
    reg  [3:0] A, B;
    reg  cin;
    wire [3:0] sum;
    wire cout;

  initial begin
    $dumpfile("simulation/adder_4bit_test.vcd");
    $dumpvars(0, adder_4bit_tb);

   
end



    adder_4bit dut (
        A, B, cin, sum, cout); 

    integer i, j, k;
    reg [4:0] answer;  
    initial begin
        $display("Starting the test...\n");

        for(i=0;i<16;i++) begin
            for(j=0;j<16;j++) begin //checking all combinations
                for(k=0;k<2; k++) begin
                    A = i;
                    B = j;
                    cin = k;

                    #5;  

                    answer = A + B + cin;
                    if({cout, sum} == answer)//compare the outputs 
                        $display("PASS  A=%0d,B=%0d,Cin=%0d,Sum=%0d",
                                  A, B, cin, answer);
                    else
                       $display("FAIL A=%0d,B=%0,Cin=%0d,Got=%b%b  Expected=%b",
                                  A, B, cin, cout, sum, answer);

                end
            end
        end

        $display("\n All tests done");
        $finish;
    end

endmodule

4-bit-ALU-Verilog/simulation/adder_4bit_test.vcd
$date
	Sun May 17 16:07:40 2026
$end
$version
	Icarus Verilog
$end
$timescale
	1ps
$end
$scope module adder_4bit_tb $end
$var wire 4 ! sum [3:0] $end
$var wire 1 " cout $end
$var reg 4 # A [3:0] $end
$var reg 4 $ B [3:0] $end
$var reg 5 % answer [4:0] $end
$var reg 1 & cin $end
$var integer 32 ' i [31:0] $end
$var integer 32 ( j [31:0] $end
$var integer 32 ) k [31:0] $end
$scope module dut $end
$var wire 4 * A [3:0] $end
$var wire 4 + B [3:0] $end
$var wire 1 & cin $end
$var wire 4 , sum [3:0] $end
$var wire 1 " cout $end
$var wire 1 - a3 $end
$var wire 1 . a2 $end
$var wire 1 / a1 $end
$scope module add1 $end
$var wire 1 0 a $end
$var wire 1 1 b $end
$var wire 1 & cin $end
$var wire 1 / cout $end
$var wire 1 2 sum $end
$upscope $end
$scope module add2 $end
$var wire 1 3 a $end
$var wire 1 4 b $end
$var wire 1 / cin $end
$var wire 1 . cout $end
$var wire 1 5 sum $end
$upscope $end
$scope module add3 $end
$var wire 1 6 a $end
$var wire 1 7 b $end
$var wire 1 . cin $end
$var wire 1 - cout $end
$var wire 1 8 sum $end
$upscope $end
$scope module add4 $end
$var wire 1 9 a $end
$var wire 1 : b $end
$var wire 1 - cin $end
$var wire 1 " cout $end
$var wire 1 ; sum $end
$upscope $end
$upscope $end
$upscope $end
$enddefinitions $end
$comment Show the parameter values. $end
$dumpall
$end
#0
$dumpvars
0;
0:
09
08
07
06
05
04
03
02
01
00
0/
0.
0-
b0 ,
b0 +
b0 *
b0 )
b0 (
b0 '
0&
bx %
b0 $
b0 #
0"
b0 !
$end
#5000
b1 !
b1 ,
12
1&
b1 )
b0 %
#10000
b1 !
b1 ,
12
11
0&
b1 $
b1 +
b1 (
b0 )
b1 %
#15000
15
1/
b10 !
b10 ,
02
1&
b1 )
#20000
08
0.
0/
15
b10 !
b10 ,
02
01
14
0&
b10 $
b10 +
b10 (
b0 )
b10 %
#25000
b11 !
b11 ,
12
1&
b1 )
#30000
b11 !
b11 ,
12
11
0&
b11 $
b11 +
b11 (
b0 )
b11 %
#35000
18
1.
05
1/
b100 !
b100 ,
02
1&
b1 )
#40000
0;
0.
0-
0/
05
18
b100 !
b100 ,
02
01
04
17
0&
b100 $
b100 +
b100 (
b0 )
b100 %
#45000
b101 !
b101 ,
12
1&
b1 )
#50000
b101 !
b101 ,
12
11
0&
b101 $
b101 +
b101 (
b0 )
b101 %
#55000
15
1/
b110 !
b110 ,
02
1&
b1 )
#60000
0;
0-
18
0.
0/
15
b110 !
b110 ,
02
01
14
0&
b110 $
b110 +
b110 (
b0 )
b110 %
#65000
b111 !
b111 ,
12
1&
b1 )
#70000
b111 !
b111 ,
12
11
0&
b111 $
b111 +
b111 (
b0 )
b111 %
#75000
1;
1-
08
1.
05
1/
b1000 !
b1000 ,
02
1&
b1 )
#80000
0.
0-
0"
0/
05
08
1;
b1000 !
b1000 ,
02
01
04
07
1:
0&
b1000 $
b1000 +
b1000 (
b0 )
b1000 %
#85000
b1001 !
b1001 ,
12
1&
b1 )
#90000
b1001 !
b1001 ,
12
11
0&
b1001 $
b1001 +
b1001 (
b0 )
b1001 %
#95000
15
1/
b1010 !
b1010 ,
02
1&
b1 )
#100000
08
0.
0/
15
b1010 !
b1010 ,
02
01
14
0&
b1010 $
b1010 +
b1010 (
b0 )
b1010 %
#105000
b1011 !
b1011 ,
12
1&
b1 )
#110000
b1011 !
b1011 ,
12
11
0&
b1011 $
b1011 +
b1011 (
b0 )
b1011 %
#115000
18
1.
05
1/
b1100 !
b1100 ,
02
1&
b1 )
#120000
0"
1;
0.
0-
0/
05
18
b1100 !
b1100 ,
02
01
04
17
0&
b1100 $
b1100 +
b1100 (
b0 )
b1100 %
#125000
b1101 !
b1101 ,
12
1&
b1 )
#130000
b1101 !
b1101 ,
12
11
0&
b1101 $
b1101 +
b1101 (
b0 )
b1101 %
#135000
15
1/
b1110 !
b1110 ,
02
1&
b1 )
#140000
0"
1;
0-
18
0.
0/
15
b1110 !
b1110 ,
02
01
14
0&
b1110 $
b1110 +
b1110 (
b0 )
b1110 %
#145000
b1111 !
b1111 ,
12
1&
b1 )
#150000
b1111 !
b1111 ,
12
11
0&
b1111 $
b1111 +
b1111 (
b0 )
b1111 %
#155000
1"
0;
1-
08
1.
05
1/
b0 !
b0 ,
02
1&
b1 )
#160000
0.
0-
0"
0/
05
08
0;
b1 !
b1 ,
12
01
04
07
0:
10
0&
b0 $
b0 +
b1 #
b1 *
b1 '
b0 (
b0 )
b10000 %
#165000
15
1/
b10 !
b10 ,
02
1&
b1 )
b1 %
#170000
15
1/
b10 !
b10 ,
02
11
0&
b1 $
b1 +
b1 (
b0 )
b10 %
#175000
b11 !
b11 ,
12
1&
b1 )
#180000
08
0.
0/
15
b11 !
b11 ,
12
01
14
0&
b10 $
b10 +
b10 (
b0 )
b11 %
#185000
18
1.
05
1/
b100 !
b100 ,
02
1&
b1 )
#190000
18
1.
05
1/
b100 !
b100 ,
02
11
0&
b11 $
b11 +
b11 (
b0 )
b100 %
#195000
b101 !
b101 ,
12
1&
b1 )
#200000
0;
0.
0-
0/
05
18
b101 !
b101 ,
12
01
04
17
0&
b100 $
b100 +
b100 (
b0 )
b101 %
#205000
15
1/
b110 !
b110 ,
02
1&
b1 )
#210000
15
1/
b110 !
b110 ,
02
11
0&
b101 $
b101 +
b101 (
b0 )
b110 %
#215000
b111 !
b111 ,
12
1&
b1 )
#220000
0;
0-
18
0.
0/
15
b111 !
b111 ,
12
01
14
0&
b110 $
b110 +
b110 (
b0 )
b111 %
#225000
1;
1-
08
1.
05
1/
b1000 !
b1000 ,
02
1&
b1 )
#230000
1;
1-
08
1.
05
1/
b1000 !
b1000 ,
02
11
0&
b111 $
b111 +
b111 (
b0 )
b1000 %
#235000
b1001 !
b1001 ,
12
1&
b1 )
#240000
0.
0-
0"
0/
05
08
1;
b1001 !
b1001 ,
12
01
04
07
1:
0&
b1000 $
b1000 +
b1000 (
b0 )
b1001 %
#245000
15
1/
b1010 !
b1010 ,
02
1&
b1 )
#250000
15
1/
b1010 !
b1010 ,
02
11
0&
b1001 $
b1001 +
b1001 (
b0 )
b1010 %
#255000
b1011 !
b1011 ,
12
1&
b1 )
#260000
08
0.
0/
15
b1011 !
b1011 ,
12
01
14
0&
b1010 $
b1010 +
b1010 (
b0 )
b1011 %
#265000
18
1.
05
1/
b1100 !
b1100 ,
02
1&
b1 )
#270000
18
1.
05
1/
b1100 !
b1100 ,
02
11
0&
b1011 $
b1011 +
b1011 (
b0 )
b1100 %
#275000
b1101 !
b1101 ,
12
1&
b1 )
#280000
0"
1;
0.
0-
0/
05
18
b1101 !
b1101 ,
12
01
04
17
0&
b1100 $
b1100 +
b1100 (
b0 )
b1101 %
#285000
15
1/
b1110 !
b1110 ,
02
1&
b1 )
#290000
15
1/
b1110 !
b1110 ,
02
11
0&
b1101 $
b1101 +
b1101 (
b0 )
b1110 %
#295000
b1111 !
b1111 ,
12
1&
b1 )
#300000
0"
1;
0-
18
0.
0/
15
b1111 !
b1111 ,
12
01
14
0&
b1110 $
b1110 +
b1110 (
b0 )
b1111 %
#305000
1"
0;
1-
08
1.
05
1/
b0 !
b0 ,
02
1&
b1 )
#310000
1"
0;
1-
08
1.
05
1/
b0 !
b0 ,
02
11
0&
b1111 $
b1111 +
b1111 (
b0 )
b10000 %
#315000
b1 !
b1 ,
12
1&
b1 )
#320000
0.
15
0-
0"
0/
08
0;
b10 !
b10 ,
02
01
04
07
0:
00
13
0&
b0 $
b0 +
b10 #
b10 *
b10 '
b0 (
b0 )
b10001 %
#325000
b11 !
b11 ,
12
1&
b1 )
b10 %
#330000
b11 !
b11 ,
12
11
0&
b1 $
b1 +
b1 (
b0 )
b11 %
#335000
18
1.
05
1/
b100 !
b100 ,
02
1&
b1 )
#340000
0/
05
b100 !
b100 ,
02
01
14
0&
b10 $
b10 +
b10 (
b0 )
b100 %
#345000
b101 !
b101 ,
12
1&
b1 )
#350000
b101 !
b101 ,
12
11
0&
b11 $
b11 +
b11 (
b0 )
b101 %
#355000
15
1/
b110 !
b110 ,
02
1&
b1 )
#360000
0.
0;
0-
0/
15
18
b110 !
b110 ,
02
01
04
17
0&
b100 $
b100 +
b100 (
b0 )
b110 %
#365000
b111 !
b111 ,
12
1&
b1 )
#370000
b111 !
b111 ,
12
11
0&
b101 $
b101 +
b101 (
b0 )
b111 %
#375000
1;
1-
08
1.
05
1/
b1000 !
b1000 ,
02
1&
b1 )
#380000
0/
05
b1000 !
b1000 ,
02
01
14
0&
b110 $
b110 +
b110 (
b0 )
b1000 %
#385000
b1001 !
b1001 ,
12
1&
b1 )
#390000
b1001 !
b1001 ,
12
11
0&
b111 $
b111 +
b111 (
b0 )
b1001 %
#395000
15
1/
b1010 !
b1010 ,
02
1&
b1 )
#400000
0.
0-
0"
0/
15
08
1;
b1010 !
b1010 ,
02
01
04
07
1:
0&
b1000 $
b1000 +
b1000 (
b0 )
b1010 %
#405000
b1011 !
b1011 ,
12
1&
b1 )
#410000
b1011 !
b1011 ,
12
11
0&
b1001 $
b1001 +
b1001 (
b0 )
b1011 %
#415000
18
1.
05
1/
b1100 !
b1100 ,
02
1&
b1 )
#420000
0/
05
b1100 !
b1100 ,
02
01
14
0&
b1010 $
b1010 +
b1010 (
b0 )
b1100 %
#425000
b1101 !
b1101 ,
12
1&
b1 )
#430000
b1101 !
b1101 ,
12
11
0&
b1011 $
b1011 +
b1011 (
b0 )
b1101 %
#435000
15
1/
b1110 !
b1110 ,
02
1&
b1 )
#440000
0"
0.
1;
0-
0/
15
18
b1110 !
b1110 ,
02
01
04
17
0&
b1100 $
b1100 +
b1100 (
b0 )
b1110 %
#445000
b1111 !
b1111 ,
12
1&
b1 )
#450000
b1111 !
b1111 ,
12
11
0&
b1101 $
b1101 +
b1101 (
b0 )
b1111 %
#455000
1"
0;
1-
08
1.
05
1/
b0 !
b0 ,
02
1&
b1 )
#460000
0/
05
b0 !
b0 ,
02
01
14
0&
b1110 $
b1110 +
b1110 (
b0 )
b10000 %
#465000
b1 !
b1 ,
12
1&
b1 )
#470000
b1 !
b1 ,
12
11
0&
b1111 $
b1111 +
b1111 (
b0 )
b10001 %
#475000
15
1/
b10 !
b10 ,
02
1&
b1 )
#480000
0.
0-
0"
0/
15
08
0;
b11 !
b11 ,
12
01
04
07
0:
10
0&
b0 $
b0 +
b11 #
b11 *
b11 '
b0 (
b0 )
b10010 %
#485000
18
1.
05
1/
b100 !
b100 ,
02
1&
b1 )
b11 %
#490000
18
1.
05
1/
b100 !
b100 ,
02
11
0&
b1 $
b1 +
b1 (
b0 )
b100 %
#495000
b101 !
b101 ,
12
1&
b1 )
#500000
0/
05
b101 !
b101 ,
12
01
14
0&
b10 $
b10 +
b10 (
b0 )
b101 %
#505000
15
1/
b110 !
b110 ,
02
1&
b1 )
#510000
15
1/
b110 !
b110 ,
02
11
0&
b11 $
b11 +
b11 (
b0 )
b110 %
#515000
b111 !
b111 ,
12
1&
b1 )
#520000
0.
0;
0-
0/
15
18
b111 !
b111 ,
12
01
04
17
0&
b100 $
b100 +
b100 (
b0 )
b111 %
#525000
1;
1-
08
1.
05
1/
b1000 !
b1000 ,
02
1&
b1 )
#530000
1;
1-
08
1.
05
1/
b1000 !
b1000 ,
02
11
0&
b101 $
b101 +
b101 (
b0 )
b1000 %
#535000
b1001 !
b1001 ,
12
1&
b1 )
#540000
0/
05
b1001 !
b1001 ,
12
01
14
0&
b110 $
b110 +
b110 (
b0 )
b1001 %
#545000
15
1/
b1010 !
b1010 ,
02
1&
b1 )
#550000
15
1/
b1010 !
b1010 ,
02
11
0&
b111 $
b111 +
b111 (
b0 )
b1010 %
#555000
b1011 !
b1011 ,
12
1&
b1 )
#560000
0.
0-
0"
0/
15
08
1;
b1011 !
b1011 ,
12
01
04
07
1:
0&
b1000 $
b1000 +
b1000 (
b0 )
b1011 %
#565000
18
1.
05
1/
b1100 !
b1100 ,
02
1&
b1 )
#570000
18
1.
05
1/
b1100 !
b1100 ,
02
11
0&
b1001 $
b1001 +
b1001 (
b0 )
b1100 %
#575000
b1101 !
b1101 ,
12
1&
b1 )
#580000
0/
05
b1101 !
b1101 ,
12
01
14
0&
b1010 $
b1010 +
b1010 (
b0 )
b1101 %
#585000
15
1/
b1110 !
b1110 ,
02
1&
b1 )
#590000
15
1/
b1110 !
b1110 ,
02
11
0&
b1011 $
b1011 +
b1011 (
b0 )
b1110 %
#595000
b1111 !
b1111 ,
12
1&
b1 )
#600000
0"
0.
1;
0-
0/
15
18
b1111 !
b1111 ,
12
01
04
17
0&
b1100 $
b1100 +
b1100 (
b0 )
b1111 %
#605000
1"
0;
1-
08
1.
05
1/
b0 !
b0 ,
02
1&
b1 )
#610000
1"
0;
1-
08
1.
05
1/
b0 !
b0 ,
02
11
0&
b1101 $
b1101 +
b1101 (
b0 )
b10000 %
#615000
b1 !
b1 ,
12
1&
b1 )
#620000
0/
05
b1 !
b1 ,
12
01
14
0&
b1110 $
b1110 +
b1110 (
b0 )
b10001 %
#625000
15
1/
b10 !
b10 ,
02
1&
b1 )
#630000
15
1/
b10 !
b10 ,
02
11
0&
b1111 $
b1111 +
b1111 (
b0 )
b10010 %
#635000
b11 !
b11 ,
12
1&
b1 )
#640000
0-
18
05
0"
0.
0/
0;
b100 !
b100 ,
02
01
04
07
0:
00
03
16
0&
b0 $
b0 +
b100 #
b100 *
b100 '
b0 (
b0 )
b10011 %
#645000
b101 !
b101 ,
12
1&
b1 )
b100 %
#650000
b101 !
b101 ,
12
11
0&
b1 $
b1 +
b1 (
b0 )
b101 %
#655000
15
1/
b110 !
b110 ,
02
1&
b1 )
#660000
0;
0-
18
0.
0/
15
b110 !
b110 ,
02
01
14
0&
b10 $
b10 +
b10 (
b0 )
b110 %
#665000
b111 !
b111 ,
12
1&
b1 )
#670000
b111 !
b111 ,
12
11
0&
b11 $
b11 +
b11 (
b0 )
b111 %
#675000
1;
1-
08
1.
05
1/
b1000 !
b1000 ,
02
1&
b1 )
#680000
0.
0/
05
08
b1000 !
b1000 ,
02
01
04
17
0&
b100 $
b100 +
b100 (
b0 )
b1000 %
#685000
b1001 !
b1001 ,
12
1&
b1 )
#690000
b1001 !
b1001 ,
12
11
0&
b101 $
b101 +
b101 (
b0 )
b1001 %
#695000
15
1/
b1010 !
b1010 ,
02
1&
b1 )
#700000
08
0.
0/
15
b1010 !
b1010 ,
02
01
14
0&
b110 $
b110 +
b110 (
b0 )
b1010 %
#705000
b1011 !
b1011 ,
12
1&
b1 )
#710000
b1011 !
b1011 ,
12
11
0&
b111 $
b111 +
b111 (
b0 )
b1011 %
#715000
18
1.
05
1/
b1100 !
b1100 ,
02
1&
b1 )
#720000
0-
0.
0"
0/
05
18
1;
b1100 !
b1100 ,
02
01
04
07
1:
0&
b1000 $
b1000 +
b1000 (
b0 )
b1100 %
#725000
b1101 !
b1101 ,
12
1&
b1 )
#730000
b1101 !
b1101 ,
12
11
0&
b1001 $
b1001 +
b1001 (
b0 )
b1101 %
#735000
15
1/
b1110 !
b1110 ,
02
1&
b1 )
#740000
0"
1;
0-
18
0.
0/
15
b1110 !
b1110 ,
02
01
14
0&
b1010 $
b1010 +
b1010 (
b0 )
b1110 %
#745000
b1111 !
b1111 ,
12
1&
b1 )
#750000
b1111 !
b1111 ,
12
11
0&
b1011 $
b1011 +
b1011 (
b0 )
b1111 %
#755000
1"
0;
1-
08
1.
05
1/
b0 !
b0 ,
02
1&
b1 )
#760000
0.
0/
05
08
b0 !
b0 ,
02
01
04
17
0&
b1100 $
b1100 +
b1100 (
b0 )
b10000 %
#765000
b1 !
b1 ,
12
1&
b1 )
#770000
b1 !
b1 ,
12
11
0&
b1101 $
b1101 +
b1101 (
b0 )
b10001 %
#775000
15
1/
b10 !
b10 ,
02
1&
b1 )
#780000
08
0.
0/
15
b10 !
b10 ,
02
01
14
0&
b1110 $
b1110 +
b1110 (
b0 )
b10010 %
#785000
b11 !
b11 ,
12
1&
b1 )
#790000
b11 !
b11 ,
12
11
0&
b1111 $
b1111 +
b1111 (
b0 )
b10011 %
#795000
18
1.
05
1/
b100 !
b100 ,
02
1&
b1 )
#800000
0-
0.
0"
0/
05
18
0;
b101 !
b101 ,
12
01
04
07
0:
10
0&
b0 $
b0 +
b101 #
b101 *
b101 '
b0 (
b0 )
b10100 %
#805000
15
1/
b110 !
b110 ,
02
1&
b1 )
b101 %
#810000
15
1/
b110 !
b110 ,
02
11
0&
b1 $
b1 +
b1 (
b0 )
b110 %
#815000
b111 !
b111 ,
12
1&
b1 )
#820000
0;
0-
18
0.
0/
15
b111 !
b111 ,
12
01
14
0&
b10 $
b10 +
b10 (
b0 )
b111 %
#825000
1;
1-
08
1.
05
1/
b1000 !
b1000 ,
02
1&
b1 )
#830000
1;
1-
08
1.
05
1/
b1000 !
b1000 ,
02
11
0&
b11 $
b11 +
b11 (
b0 )
b1000 %
#835000
b1001 !
b1001 ,
12
1&
b1 )
#840000
0.
0/
05
08
b1001 !
b1001 ,
12
01
04
17
0&
b100 $
b100 +
b100 (
b0 )
b1001 %
#845000
15
1/
b1010 !
b1010 ,
02
1&
b1 )
#850000
15
1/
b1010 !
b1010 ,
02
11
0&
b101 $
b101 +
b101 (
b0 )
b1010 %
#855000
b1011 !
b1011 ,
12
1&
b1 )
#860000
08
0.
0/
15
b1011 !
b1011 ,
12
01
14
0&
b110 $
b110 +
b110 (
b0 )
b1011 %
#865000
18
1.
05
1/
b1100 !
b1100 ,
02
1&
b1 )
#870000
18
1.
05
1/
b1100 !
b1100 ,
02
11
0&
b111 $
b111 +
b111 (
b0 )
b1100 %
#875000
b1101 !
b1101 ,
12
1&
b1 )
#880000
0-
0.
0"
0/
05
18
1;
b1101 !
b1101 ,
12
01
04
07
1:
0&
b1000 $
b1000 +
b1000 (
b0 )
b1101 %
#885000
15
1/
b1110 !
b1110 ,
02
1&
b1 )
#890000
15
1/
b1110 !
b1110 ,
02
11
0&
b1001 $
b1001 +
b1001 (
b0 )
b1110 %
#895000
b1111 !
b1111 ,
12
1&
b1 )
#900000
0"
1;
0-
18
0.
0/
15
b1111 !
b1111 ,
12
01
14
0&
b1010 $
b1010 +
b1010 (
b0 )
b1111 %
#905000
1"
0;
1-
08
1.
05
1/
b0 !
b0 ,
02
1&
b1 )
#910000
1"
0;
1-
08
1.
05
1/
b0 !
b0 ,
02
11
0&
b1011 $
b1011 +
b1011 (
b0 )
b10000 %
#915000
b1 !
b1 ,
12
1&
b1 )
#920000
0.
0/
05
08
b1 !
b1 ,
12
01
04
17
0&
b1100 $
b1100 +
b1100 (
b0 )
b10001 %
#925000
15
1/
b10 !
b10 ,
02
1&
b1 )
#930000
15
1/
b10 !
b10 ,
02
11
0&
b1101 $
b1101 +
b1101 (
b0 )
b10010 %
#935000
b11 !
b11 ,
12
1&
b1 )
#940000
08
0.
0/
15
b11 !
b11 ,
12
01
14
0&
b1110 $
b1110 +
b1110 (
b0 )
b10011 %
#945000
18
1.
05
1/
b100 !
b100 ,
02
1&
b1 )
#950000
18
1.
05
1/
b100 !
b100 ,
02
11
0&
b1111 $
b1111 +
b1111 (
b0 )
b10100 %
#955000
b101 !
b101 ,
12
1&
b1 )
#960000
0-
0.
15
0"
0/
18
0;
b110 !
b110 ,
02
01
04
07
0:
00
13
0&
b0 $
b0 +
b110 #
b110 *
b110 '
b0 (
b0 )
b10101 %
#965000
b111 !
b111 ,
12
1&
b1 )
b110 %
#970000
b111 !
b111 ,
12
11
0&
b1 $
b1 +
b1 (
b0 )
b111 %
#975000
1;
1-
08
1.
05
1/
b1000 !
b1000 ,
02
1&
b1 )
#980000
0/
05
b1000 !
b1000 ,
02
01
14
0&
b10 $
b10 +
b10 (
b0 )
b1000 %
#985000
b1001 !
b1001 ,
12
1&
b1 )
#990000
b1001 !
b1001 ,
12
11
0&
b11 $
b11 +
b11 (
b0 )
b1001 %
#995000
15
1/
b1010 !
b1010 ,
02
1&
b1 )
#1000000
0.
0/
15
08
b1010 !
b1010 ,
02
01
04
17
0&
b100 $
b100 +
b100 (
b0 )
b1010 %
#1005000
b1011 !
b1011 ,
12
1&
b1 )
#1010000
b1011 !
b1011 ,
12
11
0&
b101 $
b101 +
b101 (
b0 )
b1011 %
#1015000
18
1.
05
1/
b1100 !
b1100 ,
02
1&
b1 )
#1020000
0/
05
b1100 !
b1100 ,
02
01
14
0&
b110 $
b110 +
b110 (
b0 )
b1100 %
#1025000
b1101 !
b1101 ,
12
1&
b1 )
#1030000
b1101 !
b1101 ,
12
11
0&
b111 $
b111 +
b111 (
b0 )
b1101 %
#1035000
15
1/
b1110 !
b1110 ,
02
1&
b1 )
#1040000
0-
0.
0"
0/
15
18
1;
b1110 !
b1110 ,
02
01
04
07
1:
0&
b1000 $
b1000 +
b1000 (
b0 )
b1110 %
#1045000
b1111 !
b1111 ,
12
1&
b1 )
#1050000
b1111 !
b1111 ,
12
11
0&
b1001 $
b1001 +
b1001 (
b0 )
b1111 %
#1055000
1"
0;
1-
08
1.
05
1/
b0 !
b0 ,
02
1&
b1 )
#1060000
0/
05
b0 !
b0 ,
02
01
14
0&
b1010 $
b1010 +
b1010 (
b0 )
b10000 %
#1065000
b1 !
b1 ,
12
1&
b1 )
#1070000
b1 !
b1 ,
12
11
0&
b1011 $
b1011 +
b1011 (
b0 )
b10001 %
#1075000
15
1/
b10 !
b10 ,
02
1&
b1 )
#1080000
0.
0/
15
08
b10 !
b10 ,
02
01
04
17
0&
b1100 $
b1100 +
b1100 (
b0 )
b10010 %
#1085000
b11 !
b11 ,
12
1&
b1 )
#1090000
b11 !
b11 ,
12
11
0&
b1101 $
b1101 +
b1101 (
b0 )
b10011 %
#1095000
18
1.
05
1/
b100 !
b100 ,
02
1&
b1 )
#1100000
0/
05
b100 !
b100 ,
02
01
14
0&
b1110 $
b1110 +
b1110 (
b0 )
b10100 %
#1105000
b101 !
b101 ,
12
1&
b1 )
#1110000
b101 !
b101 ,
12
11
0&
b1111 $
b1111 +
b1111 (
b0 )
b10101 %
#1115000
15
1/
b110 !
b110 ,
02
1&
b1 )
#1120000
0-
0.
0"
0/
15
18
0;
b111 !
b111 ,
12
01
04
07
0:
10
0&
b0 $
b0 +
b111 #
b111 *
b111 '
b0 (
b0 )
b10110 %
#1125000
1;
1-
08
1.
05
1/
b1000 !
b1000 ,
02
1&
b1 )
b111 %
#1130000
1;
1-
08
1.
05
1/
b1000 !
b1000 ,
02
11
0&
b1 $
b1 +
b1 (
b0 )
b1000 %
#1135000
b1001 !
b1001 ,
12
1&
b1 )
#1140000
0/
05
b1001 !
b1001 ,
12
01
14
0&
b10 $
b10 +
b10 (
b0 )
b1001 %
#1145000
15
1/
b1010 !
b1010 ,
02
1&
b1 )
#1150000
15
1/
b1010 !
b1010 ,
02
11
0&
b11 $
b11 +
b11 (
b0 )
b1010 %
#1155000
b1011 !
b1011 ,
12
1&
b1 )
#1160000
0.
0/
15
08
b1011 !
b1011 ,
12
01
04
17
0&
b100 $
b100 +
b100 (
b0 )
b1011 %
#1165000
18
1.
05
1/
b1100 !
b1100 ,
02
1&
b1 )
#1170000
18
1.
05
1/
b1100 !
b1100 ,
02
11
0&
b101 $
b101 +
b101 (
b0 )
b1100 %
#1175000
b1101 !
b1101 ,
12
1&
b1 )
#1180000
0/
05
b1101 !
b1101 ,
12
01
14
0&
b110 $
b110 +
b110 (
b0 )
b1101 %
#1185000
15
1/
b1110 !
b1110 ,
02
1&
b1 )
#1190000
15
1/
b1110 !
b1110 ,
02
11
0&
b111 $
b111 +
b111 (
b0 )
b1110 %
#1195000
b1111 !
b1111 ,
12
1&
b1 )
#1200000
0-
0.
0"
0/
15
18
1;
b1111 !
b1111 ,
12
01
04
07
1:
0&
b1000 $
b1000 +
b1000 (
b0 )
b1111 %
#1205000
1"
0;
1-
08
1.
05
1/
b0 !
b0 ,
02
1&
b1 )
#1210000
1"
0;
1-
08
1.
05
1/
b0 !
b0 ,
02
11
0&
b1001 $
b1001 +
b1001 (
b0 )
b10000 %
#1215000
b1 !
b1 ,
12
1&
b1 )
#1220000
0/
05
b1 !
b1 ,
12
01
14
0&
b1010 $
b1010 +
b1010 (
b0 )
b10001 %
#1225000
15
1/
b10 !
b10 ,
02
1&
b1 )
#1230000
15
1/
b10 !
b10 ,
02
11
0&
b1011 $
b1011 +
b1011 (
b0 )
b10010 %
#1235000
b11 !
b11 ,
12
1&
b1 )
#1240000
0.
0/
15
08
b11 !
b11 ,
12
01
04
17
0&
b1100 $
b1100 +
b1100 (
b0 )
b10011 %
#1245000
18
1.
05
1/
b100 !
b100 ,
02
1&
b1 )
#1250000
18
1.
05
1/
b100 !
b100 ,
02
11
0&
b1101 $
b1101 +
b1101 (
b0 )
b10100 %
#1255000
b101 !
b101 ,
12
1&
b1 )
#1260000
0/
05
b101 !
b101 ,
12
01
14
0&
b1110 $
b1110 +
b1110 (
b0 )
b10101 %
#1265000
15
1/
b110 !
b110 ,
02
1&
b1 )
#1270000
15
1/
b110 !
b110 ,
02
11
0&
b1111 $
b1111 +
b1111 (
b0 )
b10110 %
#1275000
b111 !
b111 ,
12
1&
b1 )
#1280000
0"
08
1;
05
0.
0-
0/
b1000 !
b1000 ,
02
01
04
07
0:
00
03
06
19
0&
b0 $
b0 +
b1000 #
b1000 *
b1000 '
b0 (
b0 )
b10111 %
#1285000
b1001 !
b1001 ,
12
1&
b1 )
b1000 %
#1290000
b1001 !
b1001 ,
12
11
0&
b1 $
b1 +
b1 (
b0 )
b1001 %
#1295000
15
1/
b1010 !
b1010 ,
02
1&
b1 )
#1300000
08
0.
0/
15
b1010 !
b1010 ,
02
01
14
0&
b10 $
b10 +
b10 (
b0 )
b1010 %
#1305000
b1011 !
b1011 ,
12
1&
b1 )
#1310000
b1011 !
b1011 ,
12
11
0&
b11 $
b11 +
b11 (
b0 )
b1011 %
#1315000
18
1.
05
1/
b1100 !
b1100 ,
02
1&
b1 )
#1320000
0"
1;
0.
0-
0/
05
18
b1100 !
b1100 ,
02
01
04
17
0&
b100 $
b100 +
b100 (
b0 )
b1100 %
#1325000
b1101 !
b1101 ,
12
1&
b1 )
#1330000
b1101 !
b1101 ,
12
11
0&
b101 $
b101 +
b101 (
b0 )
b1101 %
#1335000
15
1/
b1110 !
b1110 ,
02
1&
b1 )
#1340000
0"
1;
0-
18
0.
0/
15
b1110 !
b1110 ,
02
01
14
0&
b110 $
b110 +
b110 (
b0 )
b1110 %
#1345000
b1111 !
b1111 ,
12
1&
b1 )
#1350000
b1111 !
b1111 ,
12
11
0&
b111 $
b111 +
b111 (
b0 )
b1111 %
#1355000
1"
0;
1-
08
1.
05
1/
b0 !
b0 ,
02
1&
b1 )
#1360000
0.
0-
0/
05
08
0;
b0 !
b0 ,
02
01
04
07
1:
0&
b1000 $
b1000 +
b1000 (
b0 )
b10000 %
#1365000
b1 !
b1 ,
12
1&
b1 )
#1370000
b1 !
b1 ,
12
11
0&
b1001 $
b1001 +
b1001 (
b0 )
b10001 %
#1375000
15
1/
b10 !
b10 ,
02
1&
b1 )
#1380000
08
0.
0/
15
b10 !
b10 ,
02
01
14
0&
b1010 $
b1010 +
b1010 (
b0 )
b10010 %
#1385000
b11 !
b11 ,
12
1&
b1 )
#1390000
b11 !
b11 ,
12
11
0&
b1011 $
b1011 +
b1011 (
b0 )
b10011 %
#1395000
18
1.
05
1/
b100 !
b100 ,
02
1&
b1 )
#1400000
0;
0.
0-
0/
05
18
b100 !
b100 ,
02
01
04
17
0&
b1100 $
b1100 +
b1100 (
b0 )
b10100 %
#1405000
b101 !
b101 ,
12
1&
b1 )
#1410000
b101 !
b101 ,
12
11
0&
b1101 $
b1101 +
b1101 (
b0 )
b10101 %
#1415000
15
1/
b110 !
b110 ,
02
1&
b1 )
#1420000
0;
0-
18
0.
0/
15
b110 !
b110 ,
02
01
14
0&
b1110 $
b1110 +
b1110 (
b0 )
b10110 %
#1425000
b111 !
b111 ,
12
1&
b1 )
