4-bit-ALU-Verilog/src/mux_5to1_4bit.v
module mux_5to1_4bit(
  input  [3:0] in0, in1, in2, in3, in4,
  input  [2:0] select,
  output reg [3:0] result
);
  always @(*) begin
    case(select)
      3'b000: result = in0;  // ADD
      3'b001: result = in1;  // SUB
      3'b010: result = in2;  // AND
      3'b011: result = in3;  // OR
      3'b100: result = in4;  // NOT
      default: result = 4'b0000;
    endcase
  end
endmodule

4-bit-ALU-Verilog/src/not_unit.v
module not_unit(
  input  [3:0] A,
  output [3:0] result
);
  assign result[0] =~A[0];
  assign result[1] =~A[1];
  assign result[2] =~A[2];
  assign result[3] =~A[3];
endmodule

4-bit-ALU-Verilog/src/or_unit.v
module or_unit(
  input  [3:0] A, B,
  output [3:0] result
);
  assign result[0] = A[0] | B[0];
  assign result[1] = A[1] | B[1];
  assign result[2] = A[2] | B[2];
  assign result[3] = A[3] | B[3];
endmodule

4-bit-ALU-Verilog/src/and_unit.v
module and_unit(
  input  [3:0] A, B,
  output [3:0] result);
  assign result[0]=A[0]&B[0];
  assign result[1]=A[1]&B[1];
  assign result[2]=A[2]&B[2];
  assign result[3]=A[3]&B[3];
endmodule

4-bit-ALU-Verilog/src/full_adder.v
 module full_adder(
  input  a, b, cin,
  output sum, cout);
  assign sum  = a ^ b ^ cin;
  assign cout = (a & b)|(b & cin)|(a & cin);
endmodule

4-bit-ALU-Verilog/src/adder_4bit.v
module adder_4bit(input [3:0]A,B,input cin
,output [3:0] sum,output cout);
wire a1,a2,a3;
full_adder add1(A[0],B[0],cin,sum[0],a1);// inistiating 4 full adder to get a 4bit adder
full_adder add2(A[1],B[1],a1,sum[1],a2);
full_adder add3(A[2],B[2],a2,sum[2],a3);
full_adder add4(A[3],B[3],a3,sum[3],cout);
endmodule

4-bit-ALU-Verilog/src/alu_4bit.v

module alu_4bit(
  input  [3:0] A, B,
  input  [2:0] opcode,
  output [3:0] result
);
  wire [3:0] add_out, sub_out, and_out, or_out, not_out;
  wire  add_cout, sub_cout;

  adder_4bit  adder(.A(A), .B(B), .cin(1'b0), .sum(add_out), .cout(add_cout));
  adder_4bit  subber(.A(A), .B(~B),.cin(1'b1), .sum(sub_out), .cout(sub_cout));
  and_unit    ander(.A(A), .B(B),.result(and_out));
  or_unit     orer(.A(A), .B(B),.result(or_out));
  not_unit    noter(.A(A),.result(not_out));

  //Opcode feeds MUX as select line
  mux_5to1_4bit mux (
    .in0(add_out), .in1(sub_out),
    .in2(and_out),
    .in3(or_out),.in4(not_out),
    .select(opcode),
    .result(result));

endmodule

4-bit-ALU-Verilog/testbench/alu_4bit.v
`timescale 1ns/1ps

module alu_tb;

  reg  [3:0] A, B;
  reg  [2:0] opcode;
  wire [3:0] result;

  alu_4bit uut (
    .A(A),
    .B(B),
    .opcode(opcode),
    .result(result)
  );

  initial begin
    $dumpfile("simulation/alu.vcd");
    $dumpvars(0, alu_tb);
  end

  initial begin
    $display("           ALU TESTBENCH                  ");
    $display(" TIME | OPCODE |  A   |  B   | RESULT ");
  end

  initial begin
    $monitor(" %3t  |  %b   | %b | %b | %b",
              $time, opcode, A, B, result);
  end

  initial begin

    
    // ADD opcode = 000
    

    // Test 1: 3 + 4 = 7
    A = 4'd3;  B = 4'd4;  opcode = 3'b000; #10;

    // Test 2: 0 + 0 = 0
    A = 4'd0;  B = 4'd0;  opcode = 3'b000; #10;

    // Test 3: 7 + 1 = 8
    A = 4'd7;  B = 4'd1;  opcode = 3'b000; #10;

    // Test 4: 15 + 1 = 0 (wraps around)
    A = 4'd15; B = 4'd1;  opcode = 3'b000; #10;

   
    // SUB opcode = 001
    

    // Test 5: 5 - 3 = 2
    A = 4'd5;  B = 4'd3;  opcode = 3'b001; #10;

    // Test 6: 4 - 4 = 0
    A = 4'd4;  B = 4'd4;  opcode = 3'b001; #10;

    // Test 7: 2 - 5 (negative result)
    A = 4'd2;  B = 4'd5;  opcode = 3'b001; #10;

  
    // AND opcode = 010


    // Test 8: 1010 & 1100 = 1000
    A = 4'b1010; B = 4'b1100; opcode = 3'b010; #10;

    // Test 9: 1111 & 1111 = 1111
    A = 4'b1111; B = 4'b1111; opcode = 3'b010; #10;

    // Test 10: 1111 & 0000 = 0000
    A = 4'b1111; B = 4'b0000; opcode = 3'b010; #10;

    // Test 11: 0101 & 1010 = 0000 (no bits same)
    A = 4'b0101; B = 4'b1010; opcode = 3'b010; #10;

   // OR opcode = 011
  

    // Test 12: 1010 | 0101 = 1111
    A = 4'b1010; B = 4'b0101; opcode = 3'b011; #10;

    // Test 13: 0000 | 0000 = 0000
    A = 4'b0000; B = 4'b0000; opcode = 3'b011; #10;

    // Test 14: 1100 | 0011 = 1111
    A = 4'b1100; B = 4'b0011; opcode = 3'b011; #10;

    // Test 15: 1000 | 0000 = 1000
    A = 4'b1000; B = 4'b0000; opcode = 3'b011; #10;


    // NOT opcode = 100 (B is ignored)

    // Test 16: ~0000 = 1111
    A = 4'b0000; B = 4'b0000; opcode = 3'b100; #10;

    // Test 17: ~1111 = 0000
    A = 4'b1111; B = 4'b0000; opcode = 3'b100; #10;

    // Test 18: ~1010 = 0101
    A = 4'b1010; B = 4'b0000; opcode = 3'b100; #10;

    // Test 19: ~0001 = 1110
    A = 4'b0001; B = 4'b0000; opcode = 3'b100; #10;

    // Test 20: B ignored in NOT
    A = 4'b1010; B = 4'b1111; opcode = 3'b100; #10;

   
    $display(" All  20 tests complete");

    $finish;
  end

endmodule

4-bit-ALU-Verilog/simulation/alu.vcd
$date
	Mon May 18 15:24:40 2026
$end
$version
	Icarus Verilog
$end
$timescale
	1ps
$end
$scope module alu_tb $end
$var wire 4 ! result [3:0] $end
$var reg 4 " A [3:0] $end
$var reg 4 # B [3:0] $end
$var reg 3 $ opcode [2:0] $end
$scope module uut $end
$var wire 4 % A [3:0] $end
$var wire 4 & B [3:0] $end
$var wire 3 ' opcode [2:0] $end
$var wire 4 ( sub_out [3:0] $end
$var wire 1 ) sub_cout $end
$var wire 4 * result [3:0] $end
$var wire 4 + or_out [3:0] $end
$var wire 4 , not_out [3:0] $end
$var wire 4 - and_out [3:0] $end
$var wire 4 . add_out [3:0] $end
$var wire 1 / add_cout $end
$scope module adder $end
$var wire 4 0 A [3:0] $end
$var wire 4 1 B [3:0] $end
$var wire 1 2 cin $end
$var wire 4 3 sum [3:0] $end
$var wire 1 / cout $end
$var wire 1 4 a3 $end
$var wire 1 5 a2 $end
$var wire 1 6 a1 $end
$scope module add1 $end
$var wire 1 7 a $end
$var wire 1 8 b $end
$var wire 1 2 cin $end
$var wire 1 6 cout $end
$var wire 1 9 sum $end
$upscope $end
$scope module add2 $end
$var wire 1 : a $end
$var wire 1 ; b $end
$var wire 1 6 cin $end
$var wire 1 5 cout $end
$var wire 1 < sum $end
$upscope $end
$scope module add3 $end
$var wire 1 = a $end
$var wire 1 > b $end
$var wire 1 5 cin $end
$var wire 1 4 cout $end
$var wire 1 ? sum $end
$upscope $end
$scope module add4 $end
$var wire 1 @ a $end
$var wire 1 A b $end
$var wire 1 4 cin $end
$var wire 1 / cout $end
$var wire 1 B sum $end
$upscope $end
$upscope $end
$scope module ander $end
$var wire 4 C A [3:0] $end
$var wire 4 D B [3:0] $end
$var wire 4 E result [3:0] $end
$upscope $end
$scope module mux $end
$var wire 4 F in0 [3:0] $end
$var wire 4 G in2 [3:0] $end
$var wire 3 H select [2:0] $end
$var wire 4 I in4 [3:0] $end
$var wire 4 J in3 [3:0] $end
$var wire 4 K in1 [3:0] $end
$var reg 4 L result [3:0] $end
$upscope $end
$scope module noter $end
$var wire 4 M A [3:0] $end
$var wire 4 N result [3:0] $end
$upscope $end
$scope module orer $end
$var wire 4 O A [3:0] $end
$var wire 4 P B [3:0] $end
$var wire 4 Q result [3:0] $end
$upscope $end
$scope module subber $end
$var wire 4 R A [3:0] $end
$var wire 4 S B [3:0] $end
$var wire 1 T cin $end
$var wire 4 U sum [3:0] $end
$var wire 1 ) cout $end
$var wire 1 V a3 $end
$var wire 1 W a2 $end
$var wire 1 X a1 $end
$scope module add1 $end
$var wire 1 Y a $end
$var wire 1 Z b $end
$var wire 1 T cin $end
$var wire 1 X cout $end
$var wire 1 [ sum $end
$upscope $end
$scope module add2 $end
$var wire 1 \ a $end
$var wire 1 ] b $end
$var wire 1 X cin $end
$var wire 1 W cout $end
$var wire 1 ^ sum $end
$upscope $end
$scope module add3 $end
$var wire 1 _ a $end
$var wire 1 ` b $end
$var wire 1 W cin $end
$var wire 1 V cout $end
$var wire 1 a sum $end
$upscope $end
$scope module add4 $end
$var wire 1 b a $end
$var wire 1 c b $end
$var wire 1 V cin $end
$var wire 1 ) cout $end
$var wire 1 d sum $end
$upscope $end
$upscope $end
$upscope $end
$upscope $end
$enddefinitions $end
$comment Show the parameter values. $end
$dumpall
$end
#0
$dumpvars
1d
1c
0b
1a
0`
0_
1^
1]
1\
1[
1Z
1Y
1X
1W
0V
b1111 U
1T
b1011 S
b11 R
b111 Q
b100 P
b11 O
b1100 N
b11 M
b111 L
b1111 K
b111 J
b1100 I
b0 H
b0 G
b111 F
b0 E
b100 D
b11 C
0B
0A
0@
1?
1>
0=
1<
0;
1:
19
08
17
06
05
04
b111 3
02
b100 1
b11 0
0/
b111 .
b0 -
b1100 ,
b111 +
b111 *
0)
b1111 (
b0 '
b100 &
b11 %
b0 $
b100 #
b11 "
b111 !
$end
#10000
1)
0d
1V
0a
b0 !
b0 *
b0 L
0?
09
b0 .
b0 3
b0 F
0<
0[
b0 (
b0 K
b0 U
0^
1`
b1111 ,
b1111 I
b1111 N
b0 +
b0 J
b0 Q
b1111 S
0>
07
0:
0Y
0\
b0 #
b0 &
b0 1
b0 D
b0 P
b0 "
b0 %
b0 0
b0 C
b0 M
b0 O
b0 R
#20000
1B
14
15
16
b1000 !
b1000 *
b1000 L
0<
b1000 .
b1000 3
b1000 F
0?
0[
1^
b110 (
b110 K
b110 U
1a
0Z
b1 -
b1 E
b1 G
b1000 ,
b1000 I
b1000 N
b111 +
b111 J
b111 Q
b1110 S
18
17
1:
1=
1Y
1\
1_
b1 #
b1 &
b1 1
b1 D
b1 P
b111 "
b111 %
b111 0
b111 C
b111 M
b111 O
b111 R
#30000
b0 !
b0 *
b0 L
b0 .
b0 3
b0 F
0B
1/
b1110 (
b1110 K
b1110 U
1d
b0 ,
b0 I
b0 N
b1111 +
b1111 J
b1111 Q
1@
1b
b1111 "
b1111 %
b1111 0
b1111 C
b1111 M
b1111 O
b1111 R
#40000
0a
0W
14
0?
15
b1000 .
b1000 3
b1000 F
1B
0/
1^
b10 (
b10 K
b10 U
0d
0]
b1010 ,
b1010 I
b1010 N
b111 +
b111 J
b111 Q
b10 !
b10 *
b10 L
b1100 S
1;
0:
0@
0\
0b
b1 $
b1 '
b1 H
b11 #
b11 &
b11 1
b11 D
b11 P
b101 "
b101 %
b101 0
b101 C
b101 M
b101 O
b101 R
#50000
1W
1)
0^
0d
1V
0a
05
06
0<
b1000 .
b1000 3
b1000 F
0?
b0 !
b0 *
b0 L
b0 (
b0 K
b0 U
0[
1X
1Z
1]
0`
b100 -
b100 E
b100 G
b1011 ,
b1011 I
b1011 N
b100 +
b100 J
b100 Q
b1011 S
08
0;
1>
07
0Y
b100 #
b100 &
b100 1
b100 D
b100 P
b100 "
b100 %
b100 0
b100 C
b100 M
b100 O
b100 R
#60000
0)
0X
0B
1[
04
1d
19
1<
b111 .
b111 3
b111 F
1?
b1101 !
b1101 *
b1101 L
0^
b1101 (
b1101 K
b1101 U
1a
0V
0Z
b0 -
b0 E
b0 G
b1101 ,
b1101 I
b1101 N
b111 +
b111 J
b111 Q
b1010 S
18
1:
0=
1\
0_
b101 #
b101 &
b101 1
b101 D
b101 P
b10 "
b10 %
b10 0
b10 C
b10 M
b10 O
b10 R
#70000
1^
1X
0[
1/
0)
b110 .
b110 3
b110 F
09
b1110 (
b1110 K
b1110 U
1d
1Z
0c
b1000 -
b1000 E
b1000 G
b101 ,
b101 I
b101 N
b1110 +
b1110 J
b1110 Q
b1000 !
b1000 *
b1000 L
b11 S
08
1A
1@
1b
b10 $
b10 '
b10 H
b1100 #
b1100 &
b1100 1
b1100 D
b1100 P
b1010 "
b1010 %
b1010 0
b1010 C
b1010 M
b1010 O
b1010 R
#80000
1B
1)
0^
15
16
14
0d
1<
b1110 .
b1110 3
b1110 F
1?
b1111 !
b1111 *
b1111 L
0[
b0 (
b0 K
b0 U
0a
1V
0Z
0]
b1111 -
b1111 E
b1111 G
b0 ,
b0 I
b0 N
b1111 +
b1111 J
b1111 Q
b0 S
18
1;
17
1=
1Y
1_
b1111 #
b1111 &
b1111 1
b1111 D
b1111 P
b1111 "
b1111 %
b1111 0
b1111 C
b1111 M
b1111 O
b1111 R
#90000
0/
04
05
1[
1^
1a
b1111 (
b1111 K
b1111 U
1d
06
19
1<
1?
b1111 .
b1111 3
b1111 F
1B
b0 !
b0 *
b0 L
1Z
1]
1`
1c
b0 -
b0 E
b0 G
b1111 S
08
0;
0>
0A
b0 #
b0 &
b0 1
b0 D
b0 P
#100000
0a
0W
0)
1^
b1011 (
b1011 K
b1011 U
1d
0]
0c
b1010 ,
b1010 I
b1010 N
b101 S
1;
1A
0:
0@
0\
0b
b1010 #
b1010 &
b1010 1
b1010 D
b1010 P
b101 "
b101 %
b101 0
b101 C
b101 M
b101 O
b101 R
#110000
0X
0V
1[
0^
1W
1a
b101 (
b101 K
b101 U
0d
1)
0Z
1]
0`
1c
b101 ,
b101 I
b101 N
b1111 !
b1111 *
b1111 L
b1010 S
18
0;
1>
0A
07
1:
0=
1@
0Y
1\
0_
1b
b11 $
b11 '
b11 H
b101 #
b101 &
b101 1
b101 D
b101 P
b1010 "
b1010 %
b1010 0
b1010 C
b1010 M
b1010 O
b1010 R
#120000
0a
1X
1V
0[
1W
1)
09
0?
0<
b0 .
b0 3
b0 F
0B
b0 !
b0 *
b0 L
0^
b0 (
b0 K
b0 U
0d
1Z
1`
b1111 ,
b1111 I
b1111 N
b0 +
b0 J
b0 Q
b1111 S
08
0>
0:
0@
0\
0b
b0 #
b0 &
b0 1
b0 D
b0 P
b0 "
b0 %
b0 0
b0 C
b0 M
b0 O
b0 R
#130000
0X
0W
1[
0^
19
1<
1?
b1111 .
b1111 3
b1111 F
1B
b1111 !
b1111 *
b1111 L
0a
b1001 (
b1001 K
b1001 U
1d
0Z
0]
b11 ,
b11 I
b11 N
b1111 +
b1111 J
b1111 Q
b1100 S
18
1;
1=
1@
1_
1b
b11 #
b11 &
b11 1
b11 D
b11 P
b1100 "
b1100 %
b1100 0
b1100 C
b1100 M
b1100 O
b1100 R
#140000
1W
1X
1d
0[
0^
1V
09
0<
b1000 .
b1000 3
b1000 F
0?
b1000 !
b1000 *
b1000 L
b1000 (
b1000 K
b1000 U
0a
1Z
1]
b111 ,
b111 I
b111 N
b1000 +
b1000 J
b1000 Q
b1111 S
08
0;
0=
0_
b0 #
b0 &
b0 1
b0 D
b0 P
b1000 "
b1000 %
b1000 0
b1000 C
b1000 M
b1000 O
b1000 R
#150000
b0 .
b0 3
b0 F
0B
b0 (
b0 K
b0 U
0d
b1111 ,
b1111 I
b1111 N
b0 +
b0 J
b0 Q
b1111 !
b1111 *
b1111 L
0@
0b
b100 $
b100 '
b100 H
b0 "
b0 %
b0 0
b0 C
b0 M
b0 O
b0 R
#160000
19
1<
1?
b1111 .
b1111 3
b1111 F
1B
b0 !
b0 *
b0 L
1[
1^
1a
b1111 (
b1111 K
b1111 U
1d
b0 ,
b0 I
b0 N
b1111 +
b1111 J
b1111 Q
17
1:
1=
1@
1Y
1\
1_
1b
b1111 "
b1111 %
b1111 0
b1111 C
b1111 M
b1111 O
b1111 R
#170000
09
b1010 .
b1010 3
b1010 F
0?
b101 !
b101 *
b101 L
0[
b1010 (
b1010 K
b1010 U
0a
b101 ,
b101 I
b101 N
b1010 +
b1010 J
b1010 Q
07
0=
0Y
0_
b1010 "
b1010 %
b1010 0
b1010 C
b1010 M
b1010 O
b1010 R
#180000
19
0<
b1 .
b1 3
b1 F
0B
b1110 !
b1110 *
b1110 L
1[
0^
b1 (
b1 K
b1 U
0d
b1110 ,
b1110 I
b1110 N
b1 +
b1 J
b1 Q
17
0:
0@
1Y
0\
0b
b1 "
b1 %
b1 0
b1 C
b1 M
b1 O
b1 R
#190000
1B
0W
0)
14
0X
0V
0a
15
1/
b1001 .
b1001 3
b1001 F
0?
b101 !
b101 *
b101 L
1[
1^
b1011 (
b1011 K
b1011 U
1d
0Z
0]
0`
0c
b1010 -
b1010 E
b1010 G
b101 ,
b101 I
b101 N
b1111 +
b1111 J
b1111 Q
b0 S
18
1;
1>
1A
07
1:
1@
0Y
1\
1b
b1111 #
b1111 &
b1111 1
b1111 D
b1111 P
b1010 "
b1010 %
b1010 0
b1010 C
b1010 M
b1010 O
b1010 R
